dbback/cli.py
dbback/configs.py
dbback/connec.py
dbback/snaps.py
dbback/tables.py
dbback-0.1.2.dist-info/licenses/LICENSE
dbback-0.1.2.dist-info/METADATA
dbback-0.1.2.dist-info/WHEEL
dbback-0.1.2.dist-info/entry_points.txt
dbback-0.1.2.dist-info/top_level.txt
dbback-0.1.2.dist-info/RECORD
