Metadata-Version: 2.4
Name: dbback
Version: 0.1.2
Summary: A CLI tool to manage database snapshots
Author-email: Krishnan Narayanan <krishnannarayanan05@gmail.com>
License-Expression: MIT
Keywords: cli,backup,database,mysql,postgresql,snapshots
Requires-Python: >=3.8
License-File: LICENSE
Requires-Dist: click>=8.0
Requires-Dist: mysql-connector-python>=9.0
Requires-Dist: asyncpg>=0.30
Requires-Dist: SQLAlchemy>=2.0
Requires-Dist: requests>=2.32
Dynamic: license-file
